pyo_oracle/__init__.py
pyo_oracle/_config.py
pyo_oracle/main.py
pyo_oracle/utils.py
pyo_oracle/data/.gitkeep
pyo_oracle-0.2.0.dist-info/licenses/LICENSE.md
pyo_oracle-0.2.0.dist-info/METADATA
pyo_oracle-0.2.0.dist-info/WHEEL
pyo_oracle-0.2.0.dist-info/top_level.txt
pyo_oracle-0.2.0.dist-info/RECORD
