Metadata-Version: 2.4
Name: pyo_oracle
Version: 0.2.0
Summary: Python client for the Bio-ORACLE ERDDAP server.
Author-email: Vini Salazar <vinicius.salazar@unimelb.edu.au>
Project-URL: Homepage, https://github.com/bio-oracle/pyo_oracle
Classifier: Programming Language :: Python :: 3
Classifier: License :: OSI Approved :: MIT License
Classifier: Operating System :: OS Independent
Requires-Python: >=3.7
License-File: LICENSE.md
Requires-Dist: erddapy
Dynamic: license-file
